jadepy/__init__.py
jadepy/core.py
JadePy-0.0a0.dist-info/LICENSE
JadePy-0.0a0.dist-info/METADATA
JadePy-0.0a0.dist-info/WHEEL
JadePy-0.0a0.dist-info/top_level.txt
JadePy-0.0a0.dist-info/RECORD
