Metadata-Version: 2.1
Name: JadePy
Version: 0.0a0
Summary: JadePy is a Python implementation of the JADE specification.
Home-page: https://github.com/Flashing-Blinkenlights/JadePy
Author: Blinkenlights
Author-email: blinkenlights@pm.me
License: GPLv3+
Keywords: generative,procedural,algorithmic,artificial,creativity,computing,design,generation,ai
Classifier: Development Status :: 1 - Planning
Classifier: Intended Audience :: Developers
Classifier: Intended Audience :: Education
Classifier: Intended Audience :: Science/Research
Classifier: License :: OSI Approved :: GNU General Public License v3 or later (GPLv3+)
Classifier: Natural Language :: English
Classifier: Operating System :: OS Independent
Classifier: Programming Language :: Python :: 3
Classifier: Topic :: Scientific/Engineering :: Artificial Intelligence
Classifier: Topic :: Software Development :: Libraries :: Application Frameworks
Requires-Python: >=3.7
License-File: LICENSE
Requires-Dist: numpy
Requires-Dist: scipy
